green_bit_llm/__init__.py
green_bit_llm/args_parser.py
green_bit_llm/enum.py
green_bit_llm/model.py
green_bit_llm/utils.py
green_bit_llm/version.py
green_bit_llm/common/__init__.py
green_bit_llm/common/enum.py
green_bit_llm/common/model.py
green_bit_llm/common/utils.py
green_bit_llm/evaluation/__init__.py
green_bit_llm/evaluation/datautils.py
green_bit_llm/evaluation/evaluate.py
green_bit_llm/evaluation/lmclass.py
green_bit_llm/evaluation/utils.py
green_bit_llm/inference/__init__.py
green_bit_llm/inference/chat_base.py
green_bit_llm/inference/chat_cli.py
green_bit_llm/inference/conversation.py
green_bit_llm/inference/sim_gen.py
green_bit_llm/inference/utils.py
green_bit_llm/langchain/__init__.py
green_bit_llm/langchain/chat_model.py
green_bit_llm/langchain/embedding.py
green_bit_llm/langchain/pipeline.py
green_bit_llm/patches/__init__.py
green_bit_llm/patches/deepseek_v3_moe_patch.py
green_bit_llm/patches/qwen3_moe_patch.py
green_bit_llm/routing/__init__.py
green_bit_llm/routing/confidence_scorer.py
green_bit_llm/routing/libra_router/__init__.py
green_bit_llm/routing/libra_router/ue_router/__init__.py
green_bit_llm/routing/libra_router/ue_router/database.py
green_bit_llm/routing/libra_router/ue_router/estimator.py
green_bit_llm/serve/__init__.py
green_bit_llm/serve/api/__init__.py
green_bit_llm/serve/api/v1/__init__.py
green_bit_llm/serve/api/v1/fastapi_server.py
green_bit_llm/serve/auth/__init__.py
green_bit_llm/serve/auth/api_key_auth.py
green_bit_llm/serve/auth/rate_limiter.py
green_bit_llm/sft/__init__.py
green_bit_llm/sft/finetune.py
green_bit_llm/sft/peft_lora.py
green_bit_llm/sft/trainer.py
green_bit_llm/sft/utils.py
green_bit_llm/sft/optim/__init__.py
green_bit_llm/sft/optim/adamw8bit.py
green_bit_llm/sft/optim/bnb_optimizer.py
green_bit_llm/sft/peft_utils/__init__.py
green_bit_llm/sft/peft_utils/gba_lora.py
green_bit_llm/sft/peft_utils/model.py
green_bit_llm-0.2.6.data/data/requirements.txt
green_bit_llm-0.2.6.dist-info/LICENSE
green_bit_llm-0.2.6.dist-info/METADATA
green_bit_llm-0.2.6.dist-info/WHEEL
green_bit_llm-0.2.6.dist-info/top_level.txt
green_bit_llm-0.2.6.dist-info/RECORD
