Metadata-Version: 2.2
Name: green-bit-llm
Version: 0.2.6
Summary: A toolkit for fine-tuning, inferencing, and evaluating GreenBitAI's LLMs.
Home-page: https://github.com/GreenBitAI/green-bit-llm
Author: GreenBitAI Contributors
Author-email: team@greenbit.ai
License: Apache-2.0
Requires-Python: >=3.9
License-File: LICENSE
Requires-Dist: accelerate>=0.27.2
Requires-Dist: colorama
Requires-Dist: datasets
Requires-Dist: torch>=2.0.0
Requires-Dist: sentencepiece
Requires-Dist: transformers>=4.52.4
Requires-Dist: huggingface-hub
Requires-Dist: lm-eval==0.3.0
Requires-Dist: termcolor
Requires-Dist: pillow
Requires-Dist: requests
Requires-Dist: prompt-toolkit
Requires-Dist: rich
Requires-Dist: optimum
Requires-Dist: auto-gptq
Requires-Dist: langchain-core
Requires-Dist: fastapi
Requires-Dist: uvicorn
Requires-Dist: peewee
Requires-Dist: python-dotenv
Dynamic: author
Dynamic: author-email
Dynamic: description
Dynamic: description-content-type
Dynamic: home-page
Dynamic: license
Dynamic: requires-dist
Dynamic: requires-python
Dynamic: summary
